yfbasic/__init__.py
yfbasic/models/__init__.py
yfbasic/models/chart.py
yfbasic/models/parameters.py
yfbasic/query.py
yfbasic-0.2.0.dist-info/LICENSE
yfbasic-0.2.0.dist-info/WHEEL
yfbasic-0.2.0.dist-info/METADATA
yfbasic-0.2.0.dist-info/RECORD
