Metadata-Version: 2.1
Name: yfbasic
Version: 0.2.0
Summary: Thin python wrapper to retrieve and work with Yahoo! finance data
Home-page: https://gitlab.com/jensusius/yfbasic
Keywords: yahoo,finance,stocks,investment
Author: jens
Author-email: jens.v.han@protonmail.com
Requires-Python: >=3.9,<4.0
Classifier: Programming Language :: Python :: 3
Classifier: Programming Language :: Python :: 3.9
Requires-Dist: pydantic (>=1.8.1,<2.0.0)
Requires-Dist: requests (>=2.25.1,<3.0.0)
Project-URL: Repository, https://gitlab.com/jensusius/yfbasic
